yt_auto_sys_utils/__init__.py
yt_auto_sys_utils/convert_json_to_dict.py
yt_auto_sys_utils-1.0.0.dist-info/METADATA
yt_auto_sys_utils-1.0.0.dist-info/WHEEL
yt_auto_sys_utils-1.0.0.dist-info/top_level.txt
yt_auto_sys_utils-1.0.0.dist-info/RECORD
