Metadata-Version: 2.1
Name: yt_auto_sys_utils
Version: 1.0.0
Summary: Shared library for microservices for yt auto system.
